Calculator binar/Modules/Controller/Controller.sv
module DecInputKey(
    input inputKey,
    input validCmd,
    input reset,
    input clk,
    output reg active,
    output reg mode
);
    reg [4:0] mem;
    reg [2:0] i = 3'd0;

    always@(posedge clk or posedge reset)begin
        if(reset) begin
            mem = 5'b0;
            i = 3'b0;
            active = 1'b0;
            mode = 1'b0;
        end
        else begin
            if(validCmd) begin
                if(i < 5)begin
                   mem[i] = inputKey;
                   i = i + 1;
                end
            end
            if(i == 5) begin
                if(mem[3:0]==4'b0101) begin
                    active <= 1'b1;
                    mode <= mem[4];
                    if(validCmd)
                        mode <= inputKey;
                end

                end
        end
    end

endmodule

module Control_RW_Flow (
    input validCmd,
    input RW,
    input reset,
    input clk,
    input txDone,
    input active,
    input mode,
    output reg AccessMem,
    output reg RWMem,
    output reg SampleData,
    output reg TxData,
    output reg Busy  
);


    
endmodule

Calculator binar/Modules/Controller/tb_decink.sv
module DUT;
    
    reg inputKey, validCmd, reset, clk;
    wire active, mode;

    DecInputKey decIK_dut(inputKey, validCmd, reset, clk, active, mode);

    initial begin
        $dumpfile("dump.vcd");
        $dumpvars(0, decIK_dut);
        $dumpvars(1, decIK_dut.mem);
        $dumpvars(1, decIK_dut.i);

    end
    initial begin
        #0 clk = 1'b0;
        forever #5 clk =~ clk;
    end

    initial
        begin
            #0 reset = 1'b1; inputKey = 1'b0; validCmd = 1'b0;
            #13 reset = 1'b0; validCmd = 1'b1; inputKey = 1'b1;
            #10 inputKey = 1'b0;
            #10 inputKey = 1'b1;
            #10 inputKey = 1'b0;
            #10 inputKey = 1'b1; // Mode 1
            #10 inputKey = 1'b0;
            #10 inputKey = 1'b1;
            #10 validCmd = 1'b1;
            #27 validCmd = 1'b0;

            #10 reset = 1'b1;
            #13 reset = 1'b0; validCmd = 1'b1; inputKey = 1'b1;
            #10 inputKey = 1'b0;
            #10 inputKey = 1'b1;
            #10 inputKey = 1'b0;
            #10 inputKey = 1'b0; // Mode 0
            #7 validCmd = 1'b0;

            #10 reset = 1'b1;
            #13 reset = 1'b0; validCmd = 1'b1; inputKey = 1'b1;
            #10 inputKey = 1'b0;
            #10 inputKey = 1'b0;
            #10 inputKey = 1'b1;
            #10 inputKey = 1'b0; // Incorrect sequence
            #7 validCmd = 1'b0;


            


            #200 $finish;
        end

endmodule

Calculator binar/Modules/Controller/dump.vcd
$date
	Thu Sep  7 14:56:35 2023
$end
$version
	Icarus Verilog
$end
$timescale
	1s
$end
$scope module DUT $end
$scope module decIK_dut $end
$var wire 1 ! clk $end
$var wire 1 " inputKey $end
$var wire 1 # reset $end
$var wire 1 $ validCmd $end
$var reg 1 % active $end
$var reg 3 & i [2:0] $end
$var reg 5 ' mem [4:0] $end
$var reg 1 ( mode $end
$upscope $end
$upscope $end
$enddefinitions $end
#0
$dumpvars
0(
b0 '
b0 &
0%
0$
1#
0"
0!
$end
#5
1!
#10
0!
#13
1"
1$
0#
#15
b1 &
b1 '
1!
#20
0!
#23
0"
#25
b10 &
1!
#30
0!
#33
1"
#35
b11 &
b101 '
1!
#40
0!
#43
0"
#45
b100 &
1!
#50
0!
#53
1"
#55
1(
1%
b101 &
b10101 '
1!
#60
0!
#63
0"
#65
0(
1!
#70
0!
#73
1"
#75
1(
1!
#80
0!
#85
1!
#90
0!
#95
1!
#100
0!
#105
1!
#110
0!
0$
#115
1!
#120
0(
0%
b0 &
b0 '
0!
1#
#125
1!
#130
0!
#133
1$
0#
#135
b1 &
b1 '
1!
#140
0!
#143
0"
#145
b10 &
1!
#150
0!
#153
1"
#155
b11 &
b101 '
1!
#160
0!
#163
0"
#165
b100 &
1!
#170
0!
#175
1%
b101 &
1!
#180
0!
0$
#185
1!
#190
0%
b0 &
b0 '
0!
1#
#195
1!
#200
0!
#203
1"
1$
0#
#205
b1 &
b1 '
1!
#210
0!
#213
0"
#215
b10 &
1!
#220
0!
#225
b11 &
1!
#230
0!
#233
1"
#235
b100 &
b1001 '
1!
#240
0!
#243
0"
#245
b101 &
1!
#250
0!
0$
