Calculator binar/Modules/ALU/ALU.sv
module ALU(
  input [7:0] inA,
  input [7:0] inB,
  input [3:0] sel_tmp,
  output reg [7:0] dout,
  output reg [3:0] flags
);
// Flag-ul 0 se activeaza la orice operatie daca rezultatul este 0
  always@(*)
    begin
        flags = 4'b0;
        case(sel_tmp)
            4'h0: begin //ADD
            if(inA + inB >= 256)
                begin
                flags[2] = 1'b1;
                end
            if(inA + inB == 0)
                begin
                flags[0] = 1'b1;
                end
            dout = inA + inB;
            end
            4'h1:begin //SUB
            if(inA < inB)
                begin
                flags[3] = 1'b1;
                end
            if(inA-inB == 0)
                begin
                flags[0] = 1'b1;
                end
            dout = inA-inB;
            end
            4'h2:begin //MUL
            if(inA * inB >= 256)
                begin
                flags[2] = 1'b1;
                end
            if(inA * inB == 0)
                begin
                flags[0] = 1'b1;
                end
            dout = inA * inB;
            end
            4'h3:begin //DIV
                if(inB == 0)
                    begin
                        flags[2] = 1'b1;
                        dout = 8'b0;
                    end
                else if(inA < inB)
                    begin
                        flags[3] = 1'b1;
                        dout = 8'b0;
                    end
                else
                    dout = inA / inB;

            end
            4'h4:begin //SHL
            if(inB >= 8)
                begin
                    flags[0] = 1'b1;
                    dout = 8'b0;
                end
            else
                begin
                    dout = inA << inB;
                    flags[1] = inA[7- inB + 1];
                    if(dout == 8'b0)
                        flags[0] = 1'b1;
                end
            end
            4'h5:begin //SHR
                if(inB >= 8)
                    begin
                        flags[0] = 1'b1;
                        dout = 8'b0;
                    end
                else
                    begin
                        dout = inA>>inB;
                        flags[1] = inA[inB-1];
                        if(dout == 8'b0)
                            flags[0] = 1'b1;
                    end
            end
            4'h6:begin //AND
                dout = inA & inB;
                if(dout == 8'b0)
                    flags[0] = 1'b1;
            end
            4'h7:begin //OR
                dout = inA | inB;
                if(dout == 8'b0)
                    flags[0] = 1'b1;
            end
            4'h8:begin //XOR
                dout = inA ^ inB;
                if(dout == 8'b0)
                    flags[0] = 1'b1;
            end
            4'h9:begin //NXOR
                dout = inA ~^ inB;
                if(dout == 8'b0)
                    flags[0] = 1'b1;
            end
            4'ha:begin //NAND
                dout = inA ~& inB;
                if(dout == 8'b0)
                    flags[0] = 1'b1;
            end
            4'hb:begin //NOR
                dout = inA ~| inB;
                if(dout == 8'b0)
                    flags[0] = 1'b1;
            end
            4'hc, 4'hd, 4'he, 4'hf:begin //Default
                dout = 8'b0;
                flags = 4'b0;
            end
      endcase
        
    end


endmodule

Calculator binar/Modules/ALU/testbench.sv
module DUT;

  reg [7:0] a, b;
  reg [3:0] sel;
  wire [7:0] dout;
  wire [3:0] flags;
  

  ALU alu_dut(a, b, sel, dout, flags);

  
  task write(input [7:0] at, input [7:0]bt, input [3:0] selt);
      begin
        a = at;
        b = bt;
        sel = selt;
      end
    endtask


    // Close file and finish simulation
    initial begin
        $dumpfile("dump.vcd"); // Save simulation data in VCD file
    $dumpvars(1);
  end

  initial begin
    #5 write(8'd250, 8'd8, 4'h0); //ADD overflow
    #5 write(8'd0, 8'd0, 4'h0); //ADD zero flag
    #5 write(8'd5, 8'd7, 4'h0); //ADD result 12

    #5 write(8'd5, 8'd8, 4'h1); //SUB A < B underflow
    #5 write(8'd8, 8'd8, 4'h1); //SUB zero flag
    #5 write(8'd9, 8'd5, 4'h1); //SUB result 4

    #5 write(8'd16, 8'd16, 4'h2); //MUL overflow
    #5 write(8'd0, 8'd0, 4'h2); //MUL zero flag
    #5 write(8'd6, 8'd4, 4'h2); // MUL result 24

    #5 write(8'd3, 8'd8, 4'h3); //DIV underflow
    #5 write(8'd250, 8'd0, 4'h3); //DIV error case
    #5 write(8'd9, 8'd3, 4'h3); // DIV result 3

    #5 write(8'b1100_0010, 8'd2, 4'h4); //SHL result 8 plus Carryflag = 1
    #5 write(8'd255, 8'h8, 4'h4); //SHL zero flag

    #5 write(8'b0010_0010, 8'd2, 4'h5); //SHR result 8 plus Carryflag = 1
    #5 write(8'd255, 8'h8, 4'h5); //SHR zero flag

    #5 write(8'b1010_1001, 8'b0000_1000, 4'h6); //AND result 8

    #5 write(8'b0000_0001, 8'b0000_1000, 4'h7); //OR result 9

    #5 write(8'b0000_1001, 8'b0000_1000, 4'h8); //XOR result 1

    #5 write(8'b1010_1001, 8'b0101_0111, 4'h9); //NXOR result 1

    #5 write(8'b1111_0111, 8'b1111_1111, 4'ha); //NAND result 8

    #5 write(8'b1010_1001, 8'b0000_1000, 4'hb); //NOR result 86

    #5 write(8'b1010_1001, 8'b0000_1000, 4'hc); //Default



    #200 $finish;
  end

endmodule

Calculator binar/Modules/ALU/dump.vcd
$date
	Tue Sep  5 09:11:41 2023
$end
$version
	Icarus Verilog
$end
$timescale
	1s
$end
$scope module DUT $end
$var wire 4 ! flags [3:0] $end
$var wire 8 " dout [7:0] $end
$var reg 8 # a [7:0] $end
$var reg 8 $ b [7:0] $end
$var reg 4 % sel [3:0] $end
$upscope $end
$enddefinitions $end
#0
$dumpvars
bx %
bx $
bx #
bx "
bx !
$end
#5
b10 "
b100 !
b0 %
b1000 $
b11111010 #
#10
b0 "
b1 !
b0 $
b0 #
#15
b1100 "
b0 !
b111 $
b101 #
#20
b11111101 "
b1000 !
b1 %
b1000 $
#25
b0 "
b1 !
b1000 #
#30
b100 "
b0 !
b101 $
b1001 #
#35
b0 "
b100 !
b10 %
b10000 $
b10000 #
#40
b1 !
b0 $
b0 #
#45
b11000 "
b0 !
b100 $
b110 #
#50
b0 "
b1000 !
b11 %
b1000 $
b11 #
#55
b100 !
b0 $
b11111010 #
#60
b11 "
b0 !
b11 $
b1001 #
#65
b10 !
b1000 "
b100 %
b10 $
b11000010 #
#70
b0 "
b1 !
b1000 $
b11111111 #
#75
b1000 "
b10 !
b101 %
b10 $
b100010 #
#80
b0 "
b1 !
b1000 $
b11111111 #
#85
b1000 "
b0 !
b110 %
b10101001 #
#90
b1001 "
b111 %
b1 #
#95
b1 "
b1000 %
b1001 #
#100
b1001 %
b1010111 $
b10101001 #
#105
b1000 "
b1010 %
b11111111 $
b11110111 #
#110
b1010110 "
b1011 %
b1000 $
b10101001 #
#115
b0 "
b1100 %
