Calculator binar/Modules/Frequency Divider/Frequency_Divider.sv
module Frequency_Divider(
    input[31:0] din,
    input configDiv,
    input reset,
    input clk,
    input enable,
    output reg clkOut
);

    reg [31:0] mem;
    reg [31:0] counter = 32'b0;
    always@(posedge clk or posedge reset) begin
        if(reset) begin
            mem <= 32'b1;
            clkOut <= 1'b0;
        end
        else begin
            if(~enable)begin
                clkOut <= 1'b0;
                if(configDiv)
                    mem <= din;
            end
            else begin
                counter <= counter + 32'b1; 
                if(counter >= (mem - 1))
                    counter <= 32'b0;
                clkOut <= (counter < (mem/2))? 1'b1: 1'b0;
            end

        end
    end

endmodule

Calculator binar/Modules/Frequency Divider/testbench.sv
module DUT;
    
    reg [31:0] din;
    reg configDiv, reset, clk, enable;
    wire clkOut;


    Frequency_Divider  fd_dut(din, configDiv, reset, clk, enable, clkOut);

    initial begin
        $dumpfile("dump.vcd");
        $dumpvars(0, fd_dut);
        $dumpvars(1, fd_dut.mem);
    end
    initial begin
        #0 clk = 1'b0;
        forever #6 clk =~ clk;
       
    end



    initial
        begin
            #0 din = 32'd6; configDiv = 1'b0; enable= 1'b0;  reset = 1'b1;
            #14 reset = 1'b0; configDiv = 1'b1;
            #24 enable = 1'b1; configDiv = 1'b0;
            #200 $finish;
        end

endmodule

Calculator binar/Modules/Frequency Divider/dump.vcd
$date
	Wed Sep  6 14:31:13 2023
$end
$version
	Icarus Verilog
$end
$timescale
	1s
$end
$scope module DUT $end
$scope module fd_dut $end
$var wire 1 ! clk $end
$var wire 1 " configDiv $end
$var wire 32 # din [31:0] $end
$var wire 1 $ enable $end
$var wire 1 % reset $end
$var reg 1 & clkOut $end
$var reg 32 ' counter [31:0] $end
$var reg 32 ( mem [31:0] $end
$upscope $end
$upscope $end
$enddefinitions $end
#0
$dumpvars
b1 (
b0 '
0&
1%
0$
b110 #
0"
0!
$end
#6
1!
#12
0!
#14
1"
0%
#18
b110 (
1!
#24
0!
#30
1!
#36
0!
#38
0"
1$
#42
1&
b1 '
1!
#48
0!
#54
b10 '
1!
#60
0!
#66
b11 '
1!
#72
0!
#78
0&
b100 '
1!
#84
0!
#90
b101 '
1!
#96
0!
#102
b0 '
1!
#108
0!
#114
1&
b1 '
1!
#120
0!
#126
b10 '
1!
#132
0!
#138
b11 '
1!
#144
0!
#150
0&
b100 '
1!
#156
0!
#162
b101 '
1!
#168
0!
#174
b0 '
1!
#180
0!
#186
1&
b1 '
1!
#192
0!
#198
b10 '
1!
#204
0!
#210
b11 '
1!
#216
0!
#222
0&
b100 '
1!
#228
0!
#234
b101 '
1!
