Calculator binar/Modules/Serial Transceiver/Serial_Transceiver.sv
module Serial_Transceiver #(
    parameter LENGTH = 4
)
(
    input[31:0] din,
    input sample,
    input startTx,
    input reset,
    input clk,
    input clkTx,
    output reg txDone,
    output reg txBusy,
    output reg [LENGTH-1:0] dout
);
    reg [31:0] mem;
    
    reg[5:0] i = 32 / LENGTH;

    always@(posedge clkTx or posedge clk or posedge reset) begin
        if(reset)begin
            mem = 32'b0;
            txDone = 1'b0;
            txBusy = 1'b0;
            dout = 0;
        end
        else begin
            if(clk) begin
                if(sample && ~startTx)begin
                    mem <= din;
                    i = 32/LENGTH;
                end
                else if(~sample && startTx)begin
                    txBusy <= 1'b1;
                end
                if(txDone == 1'b1)
                    txBusy <= 1'b0;
            end
            if(clkTx)begin
                if(i != 0 && txBusy == 1'b1) begin
                    dout <= mem[31:32-LENGTH];
                    mem <= mem << LENGTH;
                    i = i - 1;
                    if(i == 0)
                        txDone <= 1'b1;
                end
            end
        end
    end
    
endmodule

Calculator binar/Modules/Serial Transceiver/testbench.sv
module DUT;
    
    reg [31:0] din;
    reg sample, startTx, reset, clk, clkTx;
    wire txDone, txBusy;
    wire [4:0] dout;


    Serial_Transceiver #(5) st_dut(din, sample, startTx, reset, clk, clkTx, txDone, txBusy, dout);

    initial begin
        $dumpfile("dump.vcd");
        $dumpvars(0, st_dut);
        $dumpvars(1, st_dut.mem);
    end
    initial begin
        #0 clk = 1'b0;
        forever #10 clk =~ clk;
       
    end

    initial begin
        #0 clkTx = 1'b0;
        forever #5 clkTx =~ clkTx;
    end

    initial
        begin
            #0 din = 32'hf10f10f1; sample = 1'b0; startTx= 1'b0;  reset = 1'b1;
            #5 sample = 1'b1; reset = 1'b0;
            #20 startTx = 1'b1; sample = 1'b0;
           // #43 reset = 1'b1;
            #200 $finish;
        end

endmodule

Calculator binar/Modules/Serial Transceiver/dump.vcd
$date
	Wed Sep  6 10:06:53 2023
$end
$version
	Icarus Verilog
$end
$timescale
	1s
$end
$scope module DUT $end
$scope module st_dut $end
$var wire 1 ! clk $end
$var wire 1 " clkTx $end
$var wire 32 # din [31:0] $end
$var wire 1 $ reset $end
$var wire 1 % sample $end
$var wire 1 & startTx $end
$var reg 5 ' dout [4:0] $end
$var reg 6 ( i [5:0] $end
$var reg 32 ) mem [31:0] $end
$var reg 1 * txBusy $end
$var reg 1 + txDone $end
$upscope $end
$upscope $end
$enddefinitions $end
#0
$dumpvars
0+
0*
b0 )
b110 (
b0 '
0&
0%
1$
b11110001000011110001000011110001 #
0"
0!
$end
#5
0$
1%
1"
#10
b11110001000011110001000011110001 )
0"
1!
#15
1"
#20
0"
0!
#25
1"
0%
1&
#30
1*
0"
1!
#35
b100001111000100001111000100000 )
b11110 '
b101 (
1"
#40
0"
0!
#45
b111100010000111100010000000000 )
b100 '
b100 (
1"
#50
0"
1!
#55
b10001000011110001000000000000000 )
b111 '
b11 (
1"
#60
0"
0!
#65
b1111000100000000000000000000 )
b10001 '
b10 (
1"
#70
0"
1!
#75
b11100010000000000000000000000000 )
b1 '
b1 (
1"
#80
0"
0!
#85
1+
b1000000000000000000000000000000 )
b11100 '
b0 (
1"
#90
0*
0"
1!
#95
0*
1"
#100
0"
0!
#105
1"
#110
0*
0"
1!
#115
0*
1"
#120
0"
0!
#125
1"
#130
0*
0"
1!
#135
0*
1"
#140
0"
0!
#145
1"
#150
0*
0"
1!
#155
0*
1"
#160
0"
0!
#165
1"
#170
0*
0"
1!
#175
0*
1"
#180
0"
0!
#185
1"
#190
0*
0"
1!
#195
0*
1"
#200
0"
0!
#205
1"
#210
0*
0"
1!
#215
0*
1"
